PairwiseAlignment/__init__.py
PairwiseAlignment/run.py
PairwiseAlignment/src/__init__.py
PairwiseAlignment/src/base.py
PairwiseAlignment/src/nw.py
PairwiseAlignment/src/sw.py
PairwiseAlignment/src/utils.py
pairwiseAlignment-0.2.3.dist-info/LICENSE.txt
pairwiseAlignment-0.2.3.dist-info/METADATA
pairwiseAlignment-0.2.3.dist-info/WHEEL
pairwiseAlignment-0.2.3.dist-info/entry_points.txt
pairwiseAlignment-0.2.3.dist-info/top_level.txt
pairwiseAlignment-0.2.3.dist-info/RECORD
