Metadata-Version: 2.1
Name: pairwiseAlignment
Version: 0.2.3
Summary: Using Python to implement Needleman Wunsch and Smith Waterman algorithms
Home-page: https://github.com/Achuan-2/mini/tree/main/pairwiseAlignment
Author: Achuan-2
Author-email: achuan-2@outlook.com
License: MIT
Platform: any
Requires-Python: >=3.7
License-File: LICENSE.txt
Requires-Dist: click (==7.1.2)
Requires-Dist: matplotlib (==3.5.3)
Requires-Dist: numpy (==1.23.1)
Requires-Dist: setuptools (==61.2.0)
